pinexq/procon/__init__.py
pinexq/procon/core/__init__.py
pinexq/procon/core/cli.py
pinexq/procon/core/exceptions.py
pinexq/procon/core/helpers.py
pinexq/procon/core/logconfig.py
pinexq/procon/core/naming.py
pinexq/procon/core/types.py
pinexq/procon/dataslots/__init__.py
pinexq/procon/dataslots/abstractionlayer.py
pinexq/procon/dataslots/annotation.py
pinexq/procon/dataslots/dataslots.py
pinexq/procon/dataslots/datatypes.py
pinexq/procon/dataslots/default_reader_writer.py
pinexq/procon/dataslots/filebackend.py
pinexq/procon/dataslots/metadata.py
pinexq/procon/jobmanagement/__init__.py
pinexq/procon/jobmanagement/api_helpers.py
pinexq/procon/remote/__init__.py
pinexq/procon/remote/messages.py
pinexq/procon/remote/rabbitmq.py
pinexq/procon/runtime/__init__.py
pinexq/procon/runtime/foreman.py
pinexq/procon/runtime/job.py
pinexq/procon/runtime/settings.py
pinexq/procon/runtime/tool.py
pinexq/procon/runtime/worker.py
pinexq/procon/step/__init__.py
pinexq/procon/step/introspection.py
pinexq/procon/step/schema.py
pinexq/procon/step/step.py
pinexq/procon/step/versioning.py
pinexq_procon-2.3.0.dist-info/WHEEL
pinexq_procon-2.3.0.dist-info/METADATA
pinexq_procon-2.3.0.dist-info/RECORD
