Metadata-Version: 2.3
Name: pinexq-procon
Version: 2.3.0
Summary: Framework to create containers for DataCybernetic's PineXQ computing platform
Author: Sebastian Höfer, Carsten Blank, Mathias Reichardt
Author-email: Sebastian Höfer <hoefer@data-cybernetics.com>, Carsten Blank <blank@data-cybernetics.com>, Mathias Reichardt <reichardt@data-cybernetics.com>
License: Copyright (C) data cybernetics ssc GmbH - All Rights Reserved
Requires-Dist: aio-pika==9.5.5
Requires-Dist: click>=8.1.3
Requires-Dist: docstring-parser==0.*
Requires-Dist: httpx-caching>=0.1a4
Requires-Dist: httpx==0.*
Requires-Dist: pinexq-client>=1.0.0
Requires-Dist: pydantic>=2.10.0
Requires-Dist: pyjwt>=2.10.0
Requires-Dist: rich>=13.3.2
Requires-Dist: stamina>=24.2.0
Requires-Python: >=3.11
